{"name":"https://pvm-debugger.netlify.app/#/load/?program=0x000023656565656565bdad353f35353535adadadadad2c41adadadada4ad7b7badadadad65650101010101","initial-regs":[0,0,0,0,0,0,0,0,0,0,0,0,0],"initial-pc":0,"initial-page-map":[],"initial-memory":[],"initial-gas":20,"program":[0,0,35,101,101,101,101,101,101,189,173,53,63,53,53,53,53,173,173,173,173,173,44,65,173,173,173,173,164,173,123,123,173,173,173,173,101,101,1,1,1,1,1],"expected-status":"trap","expected-regs":[0,0,0,0,0,0,0,0,0,0,0,0,0],"expected-pc":8,"expected-gas":17,"expected-memory":[]}