{"name":"https://deploy-preview-244--pvm-debugger.netlify.app/?program=0x0000237dffffff5f5f70726f746f5f5fffff7d387d7d407d7d7d7d387d7d407d7d7d7d7d6fd50101010101","initial-regs":[0,0,0,0,0,0,0,0,0,0,0,0,0],"initial-pc":0,"initial-page-map":[],"initial-memory":[],"initial-gas":20,"program":[0,0,35,125,255,255,255,95,95,112,114,111,116,111,95,95,255,255,125,56,125,125,64,125,125,125,125,56,125,125,64,125,125,125,125,125,111,213,1,1,1,1,1],"expected-status":"trap","expected-regs":[0,0,0,0,0,0,0,0,0,0,0,0,0],"expected-pc":8,"expected-gas":17,"expected-memory":[]}