{"name":"https://pvm-debugger.netlify.app/#/load/?program=0x000037bdbdbdbdffffffffffffffffffffffffffffffffffffffffffffffffffffffffffffffffffffffffffffffffffffffffbdbdbd2abd2bff01010101010101","initial-regs":[0,0,0,0,0,0,0,0,0,0,0,0,0],"initial-pc":0,"initial-page-map":[],"initial-memory":[],"initial-gas":20,"program":[0,0,55,189,189,189,189,255,255,255,255,255,255,255,255,255,255,255,255,255,255,255,255,255,255,255,255,255,255,255,255,255,255,255,255,255,255,255,255,255,255,255,255,255,255,255,255,255,255,255,255,189,189,189,42,189,43,255,1,1,1,1,1,1,1],"expected-status":"trap","expected-regs":[0,0,0,0,0,0,0,0,0,0,0,0,0],"expected-pc":8,"expected-gas":18,"expected-memory":[]}