{"name":"https://pvm-debugger.netlify.app/#/load/?program=0x0000227b0000007e0000000000f300005d0000000000000000000000f351f3827b010000000101010101","initial-regs":[0,0,0,0,0,0,0,0,0,0,0,0,0],"initial-pc":0,"initial-page-map":[],"initial-memory":[],"initial-gas":20,"program":[0,0,34,123,0,0,0,126,0,0,0,0,0,243,0,0,93,0,0,0,0,0,0,0,0,0,0,0,243,81,243,130,123,1,0,0,0,1,1,1,1,1],"expected-status":"trap","expected-regs":[8257536,0,0,0,0,0,0,0,0,0,0,0,0],"expected-pc":8,"expected-gas":18,"expected-memory":[]}