{"name":"https://deploy-preview-244--pvm-debugger.netlify.app/?program=0x000026c2f9a0ffffffffbdbdbdbdbdbdbdbdbdbdbdbd550909090909090909090909090909095536550101010101","initial-regs":[0,0,0,0,0,0,0,0,0,0,0,0,0],"initial-pc":0,"initial-page-map":[],"initial-memory":[],"initial-gas":20,"program":[0,0,38,194,249,160,255,255,255,255,189,189,189,189,189,189,189,189,189,189,189,189,85,9,9,9,9,9,9,9,9,9,9,9,9,9,9,9,85,54,85,1,1,1,1,1],"expected-status":"trap","expected-regs":[0,0,0,0,0,0,0,0,0,0,0,0,0],"expected-pc":24,"expected-gas":16,"expected-memory":[]}