{"name":"https://pvm-debugger.netlify.app/#/load/?program=0x00002bbebebe5f5f70726f746f5f5fffbebe0000000000bebeb5b5b5ebebebebbebebebebebeffffbebebebebe01010101010101","initial-regs":[0,0,0,0,0,0,0,0,0,0,0,0,0],"initial-pc":0,"initial-page-map":[],"initial-memory":[],"initial-gas":20,"program":[0,0,43,190,190,190,95,95,112,114,111,116,111,95,95,255,190,190,0,0,0,0,0,190,190,181,181,181,235,235,235,235,190,190,190,190,190,190,255,255,190,190,190,190,190,1,1,1,1,1,1,1],"expected-status":"trap","expected-regs":[0,0,0,0,0,0,0,0,0,0,0,0,0],"expected-pc":8,"expected-gas":17,"expected-memory":[]}